taskflowai/__init__.py
taskflowai/agent.py
taskflowai/knowledgebases/__init__.py
taskflowai/knowledgebases/faiss_knowledgebase.py
taskflowai/llm.py
taskflowai/task.py
taskflowai/tools/__init__.py
taskflowai/tools/amadeus_tools.py
taskflowai/tools/audio_tools.py
taskflowai/tools/calculator_tools.py
taskflowai/tools/conversation_tools.py
taskflowai/tools/embedding_tools.py
taskflowai/tools/faiss_tools.py
taskflowai/tools/file_tools.py
taskflowai/tools/fred_tools.py
taskflowai/tools/github_tools.py
taskflowai/tools/langchain_tools.py
taskflowai/tools/matplotlib_tools.py
taskflowai/tools/pinecone_tools.py
taskflowai/tools/semantic_splitter.py
taskflowai/tools/sentence_splitter.py
taskflowai/tools/text_splitters.py
taskflowai/tools/web_tools.py
taskflowai/tools/wikipedia_tools.py
taskflowai/tools/yahoo_finance_tools.py
taskflowai/utils.py
taskflowai-0.5.13.dist-info/LICENSE
taskflowai-0.5.13.dist-info/METADATA
taskflowai-0.5.13.dist-info/WHEEL
taskflowai-0.5.13.dist-info/RECORD
