Metadata-Version: 2.1
Name: taskflowai
Version: 0.5.13
Summary: TaskFlowAI is a lightweight, open-source python framework for building LLM based pipelines and multi-agent teams
License: Apache 2.0
Author: Philippe Andre Page
Author-email: philippeandrepage@gmail.com
Requires-Python: >=3.10,<4.0
Classifier: Development Status :: 4 - Beta
Classifier: Intended Audience :: Developers
Classifier: License :: OSI Approved :: Apache Software License
Classifier: License :: Other/Proprietary License
Classifier: Operating System :: OS Independent
Classifier: Programming Language :: Python :: 3
Classifier: Programming Language :: Python :: 3.10
Classifier: Programming Language :: Python :: 3.11
Classifier: Programming Language :: Python :: 3.12
Classifier: Programming Language :: Python :: 3.13
Provides-Extra: fred-tools
Provides-Extra: langchain-tools
Provides-Extra: matplotlib-tools
Provides-Extra: yahoo-finance-tools
Requires-Dist: PyYAML
Requires-Dist: anthropic
Requires-Dist: beautifulsoup4
Requires-Dist: cohere
Requires-Dist: elevenlabs
Requires-Dist: faiss-cpu
Requires-Dist: fake-useragent
Requires-Dist: fredapi ; extra == "fred-tools"
Requires-Dist: groq
Requires-Dist: halo
Requires-Dist: igraph
Requires-Dist: langchain-community ; extra == "langchain-tools"
Requires-Dist: langchain-core ; extra == "langchain-tools"
Requires-Dist: langchain-openai ; extra == "langchain-tools"
Requires-Dist: leidenalg
Requires-Dist: lxml
Requires-Dist: matplotlib ; extra == "matplotlib-tools"
Requires-Dist: numpy
Requires-Dist: ollama
Requires-Dist: openai (>=1.0)
Requires-Dist: pinecone
Requires-Dist: pydantic (>=2.0)
Requires-Dist: python-dotenv
Requires-Dist: pyyaml
Requires-Dist: requests
Requires-Dist: sentence_splitter
Requires-Dist: tqdm
Requires-Dist: waitress
Requires-Dist: yahoofinance ; extra == "yahoo-finance-tools"
Requires-Dist: yfinance ; extra == "yahoo-finance-tools"
Project-URL: Bug Tracker, https://github.com/philippe-page/taskflowai/issues
Project-URL: Documentation, https://taskflowai.org
Project-URL: Homepage, https://github.com/philippe-page/taskflowai/
